<?xml version="1.0" ?>
<annotation>
  <folder>images</folder>
  <filename>snap146427718189_png.rf.f52f52aabb96842bd5ffc7ecf7de154c.jpg</filename>
  <path>/workspace/data/images/snap146427718189_png.rf.f52f52aabb96842bd5ffc7ecf7de154c.jpg</path>
  <source>
    <database>Unknown</database>
  </source>
  <size>
    <width>640</width>
    <height>480</height>
    <depth>3</depth>
  </size>
  <segmented>0</segmented>
  <object>
    <name>Green</name>
    <pose>Unspecified</pose>
    <truncated>0</truncated>
    <difficult>0</difficult>
    <bndbox>
      <xmin>224</xmin>
      <ymin>202</ymin>
      <xmax>344</xmax>
      <ymax>323</ymax>
    </bndbox>
  </object>
  <object>
    <name>Purple</name>
    <pose>Unspecified</pose>
    <truncated>0</truncated>
    <difficult>0</difficult>
    <bndbox>
      <xmin>396</xmin>
      <ymin>201</ymin>
      <xmax>472</xmax>
      <ymax>275</ymax>
    </bndbox>
  </object>
  <object>
    <name>Green</name>
    <pose>Unspecified</pose>
    <truncated>0</truncated>
    <difficult>0</difficult>
    <bndbox>
      <xmin>86</xmin>
      <ymin>218</ymin>
      <xmax>209</xmax>
      <ymax>333</ymax>
    </bndbox>
  </object>
  <object>
    <name>Purple</name>
    <pose>Unspecified</pose>
    <truncated>0</truncated>
    <difficult>0</difficult>
    <bndbox>
      <xmin>536</xmin>
      <ymin>158</ymin>
      <xmax>637</xmax>
      <ymax>315</ymax>
    </bndbox>
  </object>
  <object>
    <name>Purple</name>
    <pose>Unspecified</pose>
    <truncated>0</truncated>
    <difficult>0</difficult>
    <bndbox>
      <xmin>0</xmin>
      <ymin>272</ymin>
      <xmax>11</xmax>
      <ymax>365</ymax>
    </bndbox>
  </object>
</annotation>
